normal_position_combination-0.0.3.dist-info/METADATA
normal_position_combination-0.0.3.dist-info/RECORD
normal_position_combination-0.0.3.dist-info/WHEEL
normal_position_combination-0.0.3.dist-info/licenses/LICENSE
normal_position_combination/_wrapper.py
normal_position_combination/__init__.py
normal_position_combination/_cpp_impl.cpython-310-x86_64-linux-gnu.so
normal_position_combination.libs/libcholmod-8f6cf142.so.3.0.6
normal_position_combination.libs/libcamd-28bb7d13.so.2.4.1
normal_position_combination.libs/libccolamd-b4f1d742.so.2.9.1
normal_position_combination.libs/libcolamd-dc193ab4.so.2.9.1
normal_position_combination.libs/libquadmath-d6be75ba.so.0.0.0
normal_position_combination.libs/libamd-a26d1aab.so.2.4.1
normal_position_combination.libs/libsatlas-6c1f674f.so.3.10
normal_position_combination.libs/libgfortran-1f0d579a.so.5.0.0
normal_position_combination.libs/libsuitesparseconfig-e4e8c4aa.so.4.4.4
normal_position_combination.libs/libgomp-a97153a2.so.1.0.0
