Metadata-Version: 2.1
Name: normal-position-combination
Version: 0.0.3
Summary: Python Binding for Efficiently Combining Positions and Normals for Precise 3D Geometry
Author-Email: NCJ <me@ncj.wiki>
License: MIT License
Classifier: Programming Language :: Python :: 3
Classifier: License :: OSI Approved :: MIT License
Classifier: Operating System :: POSIX :: Linux
Classifier: Topic :: Multimedia :: Graphics :: 3D Modeling
Project-URL: Homepage, https://github.com/iamNCJ/normal-position-combination
Requires-Python: >=3.8
Requires-Dist: trimesh
Requires-Dist: numpy
